MofanShujuchuliXilieJiaocheng20201031/README.md
MofanShujuchuliXilieJiaocheng20201031/__init__.py
MofanShujuchuliXilieJiaocheng20201031/__main__.py
MofanShujuchuliXilieJiaocheng20201031/file.epub
MofanShujuchuliXilieJiaocheng20201031/index.html
MofanShujuchuliXilieJiaocheng20201031/css/__init__.py
MofanShujuchuliXilieJiaocheng20201031/css/annotations.css
MofanShujuchuliXilieJiaocheng20201031/css/main.css
MofanShujuchuliXilieJiaocheng20201031/css/normalize.css
MofanShujuchuliXilieJiaocheng20201031/css/popup.css
MofanShujuchuliXilieJiaocheng20201031/font/__init__.py
MofanShujuchuliXilieJiaocheng20201031/font/fontello.eot
MofanShujuchuliXilieJiaocheng20201031/font/fontello.svg
MofanShujuchuliXilieJiaocheng20201031/font/fontello.ttf
MofanShujuchuliXilieJiaocheng20201031/font/fontello.woff
MofanShujuchuliXilieJiaocheng20201031/img/__init__.py
MofanShujuchuliXilieJiaocheng20201031/img/annotator-glyph-sprite.png
MofanShujuchuliXilieJiaocheng20201031/img/annotator-icon-sprite.png
MofanShujuchuliXilieJiaocheng20201031/img/apple-touch-icon.png
MofanShujuchuliXilieJiaocheng20201031/img/cancelfullscreen.png
MofanShujuchuliXilieJiaocheng20201031/img/close.png
MofanShujuchuliXilieJiaocheng20201031/img/fullscreen.png
MofanShujuchuliXilieJiaocheng20201031/img/loader.gif
MofanShujuchuliXilieJiaocheng20201031/img/menu-icon.png
MofanShujuchuliXilieJiaocheng20201031/img/save.png
MofanShujuchuliXilieJiaocheng20201031/img/saved.png
MofanShujuchuliXilieJiaocheng20201031/img/settings-s.png
MofanShujuchuliXilieJiaocheng20201031/img/settings.png
MofanShujuchuliXilieJiaocheng20201031/img/star.png
MofanShujuchuliXilieJiaocheng20201031/js/__init__.py
MofanShujuchuliXilieJiaocheng20201031/js/epub.js
MofanShujuchuliXilieJiaocheng20201031/js/epub.min.js
MofanShujuchuliXilieJiaocheng20201031/js/epub.min.map
MofanShujuchuliXilieJiaocheng20201031/js/hooks.min.js
MofanShujuchuliXilieJiaocheng20201031/js/hooks.min.map
MofanShujuchuliXilieJiaocheng20201031/js/reader.js
mofan_shujuchuli_xilie_jiaocheng_2020_10_31-2024.3.5.0.dist-info/METADATA
mofan_shujuchuli_xilie_jiaocheng_2020_10_31-2024.3.5.0.dist-info/WHEEL
mofan_shujuchuli_xilie_jiaocheng_2020_10_31-2024.3.5.0.dist-info/entry_points.txt
mofan_shujuchuli_xilie_jiaocheng_2020_10_31-2024.3.5.0.dist-info/top_level.txt
mofan_shujuchuli_xilie_jiaocheng_2020_10_31-2024.3.5.0.dist-info/RECORD
